tirex/__init__.py
tirex/tirex.py
TIREX-0.0.2.dist-info/METADATA
TIREX-0.0.2.dist-info/WHEEL
TIREX-0.0.2.dist-info/top_level.txt
TIREX-0.0.2.dist-info/RECORD
